{"P7": {"labels": ["Blog_Vocabulary"], "postTitle": "January.13.2025", "postUrl": "post/January.13.2025.html", "createdDate": "2025-01-14", "dateLabelColor": "#0969da"}, "P6": {"labels": ["Blog_Documents"], "postTitle": "Test for upload files", "postUrl": "post/Test%20for%20upload%20files.html", "createdDate": "2025-01-09", "dateLabelColor": "#0969da"}, "P5": {"labels": ["Blog_Vocabulary"], "postTitle": "Januray.9.2015", "postUrl": "post/Januray.9.2015.html", "createdDate": "2025-01-09", "dateLabelColor": "#0969da"}, "P4": {"labels": ["Blog_Test"], "postTitle": "Python", "postUrl": "post/Python.html", "createdDate": "2025-01-06", "dateLabelColor": "#0969da"}, "P3": {"labels": ["Blog_Vocabulary"], "postTitle": "January.2.2025", "postUrl": "post/January.2.2025.html", "createdDate": "2025-01-02", "dateLabelColor": "#0969da"}, "P2": {"labels": ["Blog_Vocabulary"], "postTitle": "January.1.2025", "postUrl": "post/January.1.2025.html", "createdDate": "2025-01-01", "dateLabelColor": "#0969da"}, "labelColorDict": {"Blog_Documents": "#0052cc", "Blog_Test": "#bfd4f2", "Blog_Vocabulary": "#B37E9F", "bug": "#d73a4a", "documentation": "#0075ca", "duplicate": "#cfd3d7", "enhancement": "#a2eeef", "good first issue": "#7057ff", "help wanted": "#008672", "invalid": "#e4e669", "question": "#d876e3", "wontfix": "#ffffff"}}